somethingtest/__init__.py
somethingtest/__version__.py
somethingtest/core.py
tkcrypteo/__init__.py
tkcrypteo/__version__.py
tkcrypteo/core.py
tkcrypteo-0.3.0.dist-info/LICENSE
tkcrypteo-0.3.0.dist-info/METADATA
tkcrypteo-0.3.0.dist-info/WHEEL
tkcrypteo-0.3.0.dist-info/top_level.txt
tkcrypteo-0.3.0.dist-info/RECORD
