Metadata-Version: 2.1
Name: tkcrypteo
Version: 0.3.0
Summary: Pure-python implementation of token crypt(3) functions
Home-page: UNKNOWN
Author: Awesome Soul
Author-email: me@example.com
License: MIT
Platform: UNKNOWN
Classifier: License :: OSI Approved :: MIT License
Classifier: Programming Language :: Python
Classifier: Programming Language :: Python :: 3
Classifier: Programming Language :: Python :: 3.6
Classifier: Programming Language :: Python :: Implementation :: CPython
Classifier: Programming Language :: Python :: Implementation :: PyPy
Requires-Python: >=3.0.0
